{"metadata":{"modules":{"imports":[],"exports":{"exported":[],"specifiers":[]}},"usedHelpers":[]},"ignored":false,"code":"/**\n * Exposes the IS_MIRROR flag.\n *\n * @method velocity/isMirror\n * @for Meteor.methods\n * @return {Boolean} true if currently running in mirror\n */\nVelocity.Methods['velocity/isMirror'] = function () {\n  return !!process.env.IS_MIRROR;\n};","ast":null,"map":{"version":3,"sources":["/src/methods/isMirror.js"],"names":[],"mappings":";;;;;;;AAOA,QAAQ,CAAC,OAAO,CAAC,mBAAmB,CAAC,GAAG,YAAY;AAClD,SAAO,CAAC,CAAC,OAAO,CAAC,GAAG,CAAC,SAAS,CAAC;CAChC,CAAC","file":"/src/methods/isMirror.js.map","sourcesContent":["/**\n * Exposes the IS_MIRROR flag.\n *\n * @method velocity/isMirror\n * @for Meteor.methods\n * @return {Boolean} true if currently running in mirror\n */\nVelocity.Methods['velocity/isMirror'] = function () {\n  return !!process.env.IS_MIRROR;\n};\n"]},"hash":"eec4125e1d12b4d56756739a30f59971f510c2ec"}
